raytils/__init__.py
raytils/version.py
raytils/datasets/__init__.py
raytils/datasets/coco_creator.py
raytils/datasets/coco_fields.py
raytils/datasets/coco_visualise.py
raytils/datasets/cocoeval.py
raytils/display/__init__.py
raytils/display/open3d_display.py
raytils/display/opencv_display.py
raytils/display/utils.py
raytils/logging/__init__.py
raytils/logging/ansi.py
raytils/logging/print.py
raytils/metrics/__init__.py
raytils/metrics/regression.py
raytils/path/__init__.py
raytils/perception/__init__.py
raytils/perception/camera_intrinsics.py
raytils/perception/detectron2.py
raytils/perception/heatmaps.py
raytils/perception/image_utils.py
raytils/perception/intrinsics.py
raytils/perception/mask.py
raytils/perception/polygon.py
raytils/system/__init__.py
raytils/system/cpu.py
raytils/system/download.py
raytils/system/threads.py
raytils/time/__init__.py
raytils/time/decorator.py
raytils/time/formatting.py
raytils/time/fps.py
raytils/ui/__init__.py
raytils/ui/formatting.py
raytils/ui/selection.py
raytils-0.6.9.dist-info/LICENSE
raytils-0.6.9.dist-info/METADATA
raytils-0.6.9.dist-info/WHEEL
raytils-0.6.9.dist-info/top_level.txt
raytils-0.6.9.dist-info/RECORD
