Metadata-Version: 2.1
Name: raytils
Version: 0.6.9
Summary: Suite of utilities created by Raymond Tunstill.
Home-page: https://raymondkirk.github.io/raytils/
Author: Raymond Tunstill
Author-email: ray.tunstill@live.co.uk
License: GNU GPLv3
Platform: UNKNOWN
Classifier: Programming Language :: Python :: 3
Requires-Python: >=3.7
Requires-Dist: Cython
Requires-Dist: numpy
Requires-Dist: scikit-image
Requires-Dist: scipy
Requires-Dist: opencv-python
Requires-Dist: Pillow
Requires-Dist: tqdm
Requires-Dist: rays-pycocotools
Requires-Dist: requests
Requires-Dist: imagesize
Requires-Dist: pandas
Requires-Dist: scikit-learn
Requires-Dist: plotly
